orionapi/__init__.py
orionapi-0.3.2.dist-info/METADATA
orionapi-0.3.2.dist-info/WHEEL
orionapi-0.3.2.dist-info/RECORD
